anytools/__init__.py
anytools/assets/__init__.py
anytools/assets/assets.py
anytools/asynctools/__init__.py
anytools/asynctools/apps.py
anytools/asynctools/common.py
anytools/database/__init__.py
anytools/database/database.py
anytools/files/__init__.py
anytools/files/files.py
anytools/logging/__init__.py
anytools/logging/base.py
anytools/logging/colored.py
anytools/logging/common.py
anytools-1.0.4.dist-info/LICENSE
anytools-1.0.4.dist-info/METADATA
anytools-1.0.4.dist-info/WHEEL
anytools-1.0.4.dist-info/top_level.txt
anytools-1.0.4.dist-info/RECORD
