Metadata-Version: 2.1
Name: anytools
Version: 1.0.4
Summary: Tools and utilities for speed up programing
Author: Andrii Sapronov
Author-email: sapronov.andrey.k@gmail.com
Classifier: Programming Language :: Python :: 3
Classifier: License :: OSI Approved :: MIT License
Classifier: Operating System :: OS Independent
Requires-Python: >=3.7
License-File: LICENSE
